drivelib/__init__.py
drivelib/_version.py
drivelib/drive.py
drivelib/errors.py
drivelib-0.3.0.dist-info/LICENSE
drivelib-0.3.0.dist-info/METADATA
drivelib-0.3.0.dist-info/WHEEL
drivelib-0.3.0.dist-info/top_level.txt
drivelib-0.3.0.dist-info/RECORD
