Metadata-Version: 2.1
Name: drivelib
Version: 0.3.0
Summary: Easy access to the most common Google Drive API calls
Home-page: https://github.com/Lykos153/python-drivelib
Author: Silvio Ankermann
Author-email: silvio@booq.org
License: GPLv3
Keywords: Google Drive GoogleDrive API
Platform: UNKNOWN
Classifier: Development Status :: 3 - Alpha
Classifier: Intended Audience :: Developers
Classifier: Topic :: Software Development :: Libraries :: Python Modules
Classifier: License :: OSI Approved :: GNU General Public License v3 (GPLv3)
Classifier: Programming Language :: Python :: 3 :: Only
Classifier: Programming Language :: Python :: 3.8
Requires-Dist: google-api-python-client
Requires-Dist: google-auth-oauthlib
Requires-Dist: google-auth-httplib2
Requires-Dist: google-auth
Requires-Dist: oauth2client
Requires-Dist: expiringdict
Provides-Extra: test
Requires-Dist: coverage ; extra == 'test'
